tiktokuserspy/__init__.py
tiktokuserspy/config.py
tiktokuserspy/main.py
TikTokUsersPy-0.0.7.dist-info/METADATA
TikTokUsersPy-0.0.7.dist-info/WHEEL
TikTokUsersPy-0.0.7.dist-info/top_level.txt
TikTokUsersPy-0.0.7.dist-info/RECORD
