Metadata-Version: 2.1
Name: TikTokUsersPy
Version: 0.0.7
Summary: A WebScraper that provides tiktok user data.
Author: Jason Bodzy
Author-email: <jasonbodzy@gmail.com.com>
Keywords: python,tiktok,analytics,video,media,social
Classifier: Development Status :: 1 - Planning
Classifier: Intended Audience :: Developers
Classifier: Programming Language :: Python :: 3
Classifier: Operating System :: Unix
Classifier: Operating System :: MacOS :: MacOS X
Classifier: Operating System :: Microsoft :: Windows
Requires-Dist: selenium
